sphinxdoc/__init__.py
sphinxdoc/admin.py
sphinxdoc/decorators.py
sphinxdoc/forms.py
sphinxdoc/models.py
sphinxdoc/search_indexes.py
sphinxdoc/urls.py
sphinxdoc/validators.py
sphinxdoc/views.py
sphinxdoc/management/__init__.py
sphinxdoc/management/commands/__init__.py
sphinxdoc/management/commands/updatedoc.py
sphinxdoc/migrations/0001_initial.py
sphinxdoc/migrations/__init__.py
sphinxdoc/templates/search/indexes/sphinxdoc/document_text.txt
sphinxdoc/templates/sphinxdoc/documentation.html
sphinxdoc/templates/sphinxdoc/genindex.html
sphinxdoc/templates/sphinxdoc/modindex.html
sphinxdoc/templates/sphinxdoc/project_list.html
sphinxdoc/templates/sphinxdoc/search.html
django_sphinxdoc-2.0.0.dist-info/LICENSE.txt
django_sphinxdoc-2.0.0.dist-info/METADATA
django_sphinxdoc-2.0.0.dist-info/WHEEL
django_sphinxdoc-2.0.0.dist-info/top_level.txt
django_sphinxdoc-2.0.0.dist-info/RECORD
