Metadata-Version: 2.1
Name: django-sphinxdoc
Version: 2.0.0
Summary: Easily integrate Sphinx documentation into your website.
Home-page: https://gitlab.com/sscherfke/django-sphinxdoc
Author: Stefan Scherfke
Author-email: stefan@sofa-rockers.org
License: MIT
Platform: UNKNOWN
Classifier: Development Status :: 5 - Production/Stable
Classifier: Intended Audience :: Developers
Classifier: Natural Language :: English
Classifier: License :: OSI Approved :: MIT License
Classifier: Operating System :: OS Independent
Classifier: Environment :: Web Environment
Classifier: Framework :: Django
Classifier: Programming Language :: Python
Classifier: Programming Language :: Python :: 3
Classifier: Programming Language :: Python :: 3.6
Classifier: Programming Language :: Python :: 3.7
Classifier: Topic :: Software Development :: Libraries :: Python Modules
Classifier: Topic :: Utilities
Requires-Python: >=3.6
Requires-Dist: Django (>=2.0)
Requires-Dist: django-haystack (>=2.8.0)
